[
  {
    "year": 1913,
    "electron": 0,
    "quantum": 0,
    "atom": 2
  },
  {
    "year": 1916,
    "electron": 2,
    "quantum": 0,
    "atom": 0
  },
  {
    "year": 1919,
    "electron": 2,
    "quantum": 0,
    "atom": 0
  },
  {
    "year": 1922,
    "electron": 0,
    "quantum": 0,
    "atom": 1
  },
  {
    "year": 1923,
    "electron": 0,
    "quantum": 1,
    "atom": 0
  },
  {
    "year": 1925,
    "electron": 0,
    "quantum": 0,
    "atom": 1
  },
  {
    "year": 1926,
    "electron": 0,
    "quantum": 0,
    "atom": 1
  },
  {
    "year": 1927,
    "electron": 1,
    "quantum": 1,
    "atom": 0
  },
  {
    "year": 1928,
    "electron": 1,
    "quantum": 1,
    "atom": 0
  },
  {
    "year": 1932,
    "electron": 0,
    "quantum": 1,
    "atom": 1
  },
  {
    "year": 1933,
    "electron": 1,
    "quantum": 0,
    "atom": 0
  },
  {
    "year": 1934,
    "electron": 1,
    "quantum": 0,
    "atom": 0
  },
  {
    "year": 1937,
    "electron": 3,
    "quantum": 0,
    "atom": 0
  },
  {
    "year": 1945,
    "electron": 1,
    "quantum": 0,
    "atom": 0
  },
  {
    "year": 1947,
    "electron": 0,
    "quantum": 0,
    "atom": 1
  },
  {
    "year": 1948,
    "electron": 2,
    "quantum": 4,
    "atom": 0
  },
  {
    "year": 1949,
    "electron": 1,
    "quantum": 2,
    "atom": 0
  },
  {
    "year": 1950,
    "electron": 0,
    "quantum": 1,
    "atom": 1
  },
  {
    "year": 1956,
    "electron": 1,
    "quantum": 0,
    "atom": 0
  },
  {
    "year": 1957,
    "electron": 0,
    "quantum": 0,
    "atom": 2
  },
  {
    "year": 1958,
    "electron": 1,
    "quantum": 0,
    "atom": 0
  },
  {
    "year": 1960,
    "electron": 2,
    "quantum": 0,
    "atom": 0
  },
  {
    "year": 1961,
    "electron": 3,
    "quantum": 0,
    "atom": 0
  },
  {
    "year": 1963,
    "electron": 0,
    "quantum": 1,
    "atom": 0
  },
  {
    "year": 1964,
    "electron": 1,
    "quantum": 0,
    "atom": 0
  },
  {
    "year": 1968,
    "electron": 4,
    "quantum": 0,
    "atom": 0
  },
  {
    "year": 1969,
    "electron": 6,
    "quantum": 0,
    "atom": 0
  },
  {
    "year": 1982,
    "electron": 0,
    "quantum": 2,
    "atom": 0
  },
  {
    "year": 1983,
    "electron": 2,
    "quantum": 2,
    "atom": 0
  },
  {
    "year": 1984,
    "electron": 3,
    "quantum": 0,
    "atom": 0
  },
  {
    "year": 1988,
    "electron": 0,
    "quantum": 0,
    "atom": 1
  },
  {
    "year": 1989,
    "electron": 2,
    "quantum": 0,
    "atom": 0
  },
  {
    "year": 1994,
    "electron": 0,
    "quantum": 1,
    "atom": 0
  },
  {
    "year": 1995,
    "electron": 0,
    "quantum": 2,
    "atom": 1
  },
  {
    "year": 1996,
    "electron": 0,
    "quantum": 2,
    "atom": 2
  },
  {
    "year": 2002,
    "electron": 0,
    "quantum": 1,
    "atom": 1
  },
  {
    "year": 2009,
    "electron": 0,
    "quantum": 0,
    "atom": 1
  }
]